setup.cfg
setup.py
pyramid_mongo/__init__.py
pyramid_mongo.egg-info/PKG-INFO
pyramid_mongo.egg-info/SOURCES.txt
pyramid_mongo.egg-info/dependency_links.txt
pyramid_mongo.egg-info/entry_points.txt
pyramid_mongo.egg-info/not-zip-safe
pyramid_mongo.egg-info/requires.txt
pyramid_mongo.egg-info/top_level.txt
pyramid_mongo/tests/__init__.py
pyramid_mongo/tests/test_init.py