Metadata-Version: 1.0
Name: pyramid-mongo
Version: 0.1
Summary: Mongodb support for pyramid
Home-page: delicieuxgateau.ca
Author: Loïc Faure-Lacroix
Author-email: lamerstar@gmail.com
License: UNKNOWN
Keywords: pymongo mongodb pyramid
Platform: UNKNOWN
